ace_overlay/.DS_Store
ace_overlay/__init__.py
ace_overlay/widgets.py
ace_overlay/static/.DS_Store
ace_overlay/static/ace_overlay/.DS_Store
ace_overlay/static/ace_overlay/widget.css
ace_overlay/static/ace_overlay/widget.js
ace_overlay/static/ace_overlay/ace/ace.js
ace_overlay/static/ace_overlay/ace/ext-beautify.js
ace_overlay/static/ace_overlay/ace/ext-chromevox.js
ace_overlay/static/ace_overlay/ace/ext-elastic_tabstops_lite.js
ace_overlay/static/ace_overlay/ace/ext-emmet.js
ace_overlay/static/ace_overlay/ace/ext-error_marker.js
ace_overlay/static/ace_overlay/ace/ext-keybinding_menu.js
ace_overlay/static/ace_overlay/ace/ext-language_tools.js
ace_overlay/static/ace_overlay/ace/ext-linking.js
ace_overlay/static/ace_overlay/ace/ext-modelist.js
ace_overlay/static/ace_overlay/ace/ext-old_ie.js
ace_overlay/static/ace_overlay/ace/ext-options.js
ace_overlay/static/ace_overlay/ace/ext-searchbox.js
ace_overlay/static/ace_overlay/ace/ext-settings_menu.js
ace_overlay/static/ace_overlay/ace/ext-spellcheck.js
ace_overlay/static/ace_overlay/ace/ext-split.js
ace_overlay/static/ace_overlay/ace/ext-static_highlight.js
ace_overlay/static/ace_overlay/ace/ext-statusbar.js
ace_overlay/static/ace_overlay/ace/ext-textarea.js
ace_overlay/static/ace_overlay/ace/ext-themelist.js
ace_overlay/static/ace_overlay/ace/ext-whitespace.js
ace_overlay/static/ace_overlay/ace/keybinding-emacs.js
ace_overlay/static/ace_overlay/ace/keybinding-vim.js
ace_overlay/static/ace_overlay/ace/mode-abap.js
ace_overlay/static/ace_overlay/ace/mode-abc.js
ace_overlay/static/ace_overlay/ace/mode-actionscript.js
ace_overlay/static/ace_overlay/ace/mode-ada.js
ace_overlay/static/ace_overlay/ace/mode-apache_conf.js
ace_overlay/static/ace_overlay/ace/mode-applescript.js
ace_overlay/static/ace_overlay/ace/mode-asciidoc.js
ace_overlay/static/ace_overlay/ace/mode-assembly_x86.js
ace_overlay/static/ace_overlay/ace/mode-autohotkey.js
ace_overlay/static/ace_overlay/ace/mode-batchfile.js
django_ace_overlay-0.7.1.dist-info/DESCRIPTION.rst
django_ace_overlay-0.7.1.dist-info/METADATA
django_ace_overlay-0.7.1.dist-info/RECORD
django_ace_overlay-0.7.1.dist-info/WHEEL
django_ace_overlay-0.7.1.dist-info/metadata.json
django_ace_overlay-0.7.1.dist-info/top_level.txt
