Metadata-Version: 2.0
Name: django-ace-overlay
Version: 0.7.1
Summary: Ace editor for Django admin
Home-page: https://github.com/ninapavlich/django-ace-overlay
Author: Nina Pavlich
Author-email: nina@ninalp.com
License: MIT
Keywords: libraries,web development,cms,django,code-editor,admin
Platform: UNKNOWN
Classifier: Development Status :: 4 - Beta
Classifier: Environment :: Web Environment
Classifier: Framework :: Django
Classifier: Intended Audience :: Developers
Classifier: License :: OSI Approved :: MIT License
Classifier: Natural Language :: English
Classifier: Operating System :: OS Independent
Classifier: Programming Language :: Python
